smallsamplegenerator/Evidence.py
smallsamplegenerator/FuzzyTheory.py
smallsamplegenerator/ProbabilityTheory.py
smallsamplegenerator/__init__.py
smallsamplegenerator-1.1.0.dist-info/LICENSE.txt
smallsamplegenerator-1.1.0.dist-info/METADATA
smallsamplegenerator-1.1.0.dist-info/WHEEL
smallsamplegenerator-1.1.0.dist-info/top_level.txt
smallsamplegenerator-1.1.0.dist-info/RECORD
