Metadata-Version: 2.1
Name: smallsamplegenerator
Version: 1.1.0
Summary: A Random Data Generator under Small Sample Sizes by BUAA
Home-page: UNKNOWN
Author: BUAA
Author-email: jiangfs115200@gmail.com
License: UNKNOWN
Platform: UNKNOWN
Classifier: Development Status :: 3 - Alpha
Classifier: Intended Audience :: Developers
Classifier: Topic :: Software Development :: Build Tools
Classifier: License :: OSI Approved :: MIT License
Classifier: Programming Language :: Python :: 3
Classifier: Programming Language :: Python :: 3.6
Classifier: Programming Language :: Python :: 3.7
Classifier: Programming Language :: Python :: 3.8
Classifier: Programming Language :: Python :: 3.9
Classifier: Programming Language :: Python :: 3.10
Classifier: Programming Language :: Python :: 3 :: Only
Requires-Python: >=3.6, <4
Requires-Dist: setuptools (>=58.2.0)
Requires-Dist: numpy (>=1.19.5)
Requires-Dist: scipy (>=1.7.1)
Requires-Dist: matplotlib (>=3.4.3)
Requires-Dist: seaborn (>=0.11.2)
